deepview/flatbuffers/__init__.py
deepview/flatbuffers/builder.py
deepview/flatbuffers/compat.py
deepview/flatbuffers/encode.py
deepview/flatbuffers/number_types.py
deepview/flatbuffers/packer.py
deepview/flatbuffers/table.py
deepview/flatbuffers/util.py
deepview/rt/__init__.py
deepview/rt/common.py
deepview/rt/context.py
deepview/rt/engine.py
deepview/rt/errors.py
deepview/rt/librt.py
deepview/rt/modelclient.py
deepview/rt/tensor.py
deepview/rt/ops/__init__.py
deepview/rt/ops/activation.py
deepview/rt/ops/array.py
deepview/rt/ops/conv.py
deepview/rt/ops/math.py
deepview/rt/ops/pool.py
deepview/rt/ops/ssd.py
deepview/rtmx/__init__.py
deepview/rtmx/datatype.py
deepview/rtmx/layer.py
deepview/rtmx/model.py
deepview/rtmx/op.py
deepview/rtmx/resource.py
deepview/rtmx/tensor.py
deepview_rt-2.6.12.dist-info/METADATA
deepview_rt-2.6.12.dist-info/WHEEL
deepview_rt-2.6.12.dist-info/entry_points.txt
deepview_rt-2.6.12.dist-info/top_level.txt
deepview_rt-2.6.12.dist-info/RECORD
