Metadata-Version: 2.1
Name: deepview-rt
Version: 2.6.12
Summary: DeepViewRT for Python
Home-page: https://embeddedml.com
Author: Au-Zone Technologies
Author-email: support@au-zone.com
License: PROPRIETARY
Platform: UNKNOWN
Requires-Dist: cffi (>=1.10.0)
Requires-Dist: future
Requires-Dist: numpy (>=1.18.0)
Requires-Dist: pathlib
Requires-Dist: six
Requires-Dist: requests (>=2.19)
Requires-Dist: enum34 ; python_version < "3.4"
Requires-Dist: typing ; python_version < "3.5"
